MANIFEST.in
account_chart.xml
l10n_chart_it_generic.xml
setup.py
./__init__.py
./__openerp__.py
data/account.account.template.csv
data/account.fiscal.position.template.csv
data/account.tax.code.template.csv
data/account.tax.template.csv
i18n/ar.po
i18n/ca.po
i18n/da.po
i18n/es.po
i18n/es_CR.po
i18n/es_MX.po
i18n/es_PY.po
i18n/es_VE.po
i18n/fr.po
i18n/gl.po
i18n/it.po
i18n/l10n_it.pot
i18n/nl.po
i18n/pt_BR.po
i18n/sl.po
i18n/tr.po
images/config_chart_l10n_it.jpeg
images/l10n_it_chart.jpeg
openerp_l10n_it.egg-info/PKG-INFO
openerp_l10n_it.egg-info/SOURCES.txt
openerp_l10n_it.egg-info/dependency_links.txt
openerp_l10n_it.egg-info/requires.txt
openerp_l10n_it.egg-info/top_level.txt
static/src/img/icon.png